__init__.py
dataset.py
logger.py
noisifier.py
problem.py
runner.py
abstract_models/__init__.py
abstract_models/base.py
abstract_models/cvxpy_diff.py
abstract_models/grbpy.py
abstract_models/grbpy_two_stage.py
concrete_models/__init__.py
concrete_models/cvxpy_knapsack.py
concrete_models/grbpy_knapsack.py
concrete_models/grbpy_shortest_path.py
concrete_models/grbpy_tsp.py
concrete_models/grbpy_two_stage_knapsack.py
concrete_models/grbpy_two_stage_weighted_set_multi_cover.py
decision_makers/__init__.py
decision_makers/base.py
decision_makers/differentiable_decision_maker.py
decision_makers/lancer_decision_maker.py
decision_makers/sfge_decision_maker.py
generate_data_functions/__init__.py
generate_data_functions/generate_data_knapsack.py
generate_data_functions/generate_data_shortest_path.py
generate_data_functions/generate_data_tsp.py
generate_data_functions/generate_data_two_stage_knapsack.py
generate_data_functions/generate_data_wsmc.py
predictors/__init__.py
predictors/base.py
predictors/multilayer_normal.py
predictors/multilayer_perceptron.py
predictors/multilayer_sample.py
predictors/truncated_normal.py
pydflt-0.1.0.dist-info/licenses/LICENSE.md
registries/__init__.py
registries/data.py
registries/decision_makers.py
registries/models.py
utils/__init__.py
utils/experiments.py
utils/load.py
utils/optuna.py
utils/reproducability.py
pydflt-0.1.0.dist-info/METADATA
pydflt-0.1.0.dist-info/WHEEL
pydflt-0.1.0.dist-info/top_level.txt
pydflt-0.1.0.dist-info/RECORD
