Metadata-Version: 2.4
Name: pydflt
Version: 0.1.0
Summary: PyDFLT
Author-email: Noah Schutte <N.J.Schutte@tudelft.nl>, Kim van den Houten <K.C.vandenhouten@tudelft.nl>, Grigorii Veviurko <G.Veviurko@tudelft.nl>
Requires-Python: >=3.10
License-File: LICENSE.md
Requires-Dist: torch>=2.7.1
Requires-Dist: cvxpy>=1.4.1
Requires-Dist: diffcp>=1.0.18
Requires-Dist: cvxpylayers>=0.1.6
Requires-Dist: numpy>=1.26.4
Requires-Dist: ortools>=9.12.4544
Requires-Dist: gurobipy>=11.0.3
Requires-Dist: pyepo~=0.3.9
Requires-Dist: pyyaml>=6.0.2
Requires-Dist: tomli>=2.0.1
Requires-Dist: wandb>=0.19.11
Requires-Dist: pandas>=2.2.3
Requires-Dist: matplotlib>=3.6.3
Requires-Dist: optuna>=4.2.1
Requires-Dist: optuna-dashboard>=0.19.0
Requires-Dist: scikit-learn>=1.6.1
Requires-Dist: scipy>=1.13.1
Requires-Dist: joblib>=1.4.2
Requires-Dist: ipywidgets>=8.1.7
Dynamic: license-file
